janeiro/__init__.py
janeiro/config.py
janeiro/logging.py
janeiro-0.0.3.dist-info/METADATA
janeiro-0.0.3.dist-info/WHEEL
janeiro-0.0.3.dist-info/top_level.txt
janeiro-0.0.3.dist-info/RECORD
